cmakelists_parsing/__init__.py
cmakelists_parsing/cmake_pprint.py
cmakelists_parsing/list_utils.py
cmakelists_parsing/parsing.py
cmakelists_parsing/rand.py
tests/__init__.py
tests/example_inputs_test.py
tests/parsing_test.py
cmakelists_parsing-0.3.1.dist-info/LICENSE
cmakelists_parsing-0.3.1.dist-info/METADATA
cmakelists_parsing-0.3.1.dist-info/WHEEL
cmakelists_parsing-0.3.1.dist-info/entry_points.txt
cmakelists_parsing-0.3.1.dist-info/top_level.txt
cmakelists_parsing-0.3.1.dist-info/RECORD
